{
	"configurations" : 
	[
		{
			"directories" : 
			[
				{
					"build" : ".",
					"jsonFile" : "directory-.-Debug-d0094a50bb2071803777.json",
					"minimumCMakeVersion" : 
					{
						"string" : "3.28"
					},
					"projectIndex" : 0,
					"source" : ".",
					"targetIndexes" : 
					[
						0
					]
				}
			],
			"name" : "Debug",
			"projects" : 
			[
				{
					"directoryIndexes" : 
					[
						0
					],
					"name" : "ZOOProjekt",
					"targetIndexes" : 
					[
						0
					]
				}
			],
			"targets" : 
			[
				{
					"directoryIndex" : 0,
					"id" : "ZOOProjekt::@6890427a1f51a3e7e1df",
					"jsonFile" : "target-ZOOProjekt-Debug-19c259e01b32a80c0bc0.json",
					"name" : "ZOOProjekt",
					"projectIndex" : 0
				}
			]
		}
	],
	"kind" : "codemodel",
	"paths" : 
	{
		"build" : "D:/ZOOProjekt/ZOOProjekt/cmake-build-debug",
		"source" : "D:/ZOOProjekt/ZOOProjekt"
	},
	"version" : 
	{
		"major" : 2,
		"minor" : 6
	}
}
